remotejob/__init__.py
remotejob-0.2.0.dist-info/METADATA
remotejob-0.2.0.dist-info/WHEEL
remotejob-0.2.0.dist-info/top_level.txt
remotejob-0.2.0.dist-info/RECORD
